beebo/__init__.py
beebo/__main__.py
beebo/acquisition.py
beebo/utils/__init__.py
beebo/utils/cholesky_inference.py
beebo-0.0.2.dist-info/METADATA
beebo-0.0.2.dist-info/WHEEL
beebo-0.0.2.dist-info/top_level.txt
beebo-0.0.2.dist-info/RECORD
