Metadata-Version: 2.1
Name: beebo
Version: 0.0.2
Summary: Batched Energy-Entropy acquistion for Bayesian optimization
Author-email: Felix Teufel <fegt@novonordisk.com>
Project-URL: Homepage, https://https://github.com/fteufel/BEE-BO
Classifier: Programming Language :: Python
Classifier: Programming Language :: Python :: 3
Requires-Python: >=3.9
Requires-Dist: botorch >=0.9.4
Requires-Dist: gpytorch >=1.11
Requires-Dist: scipy >=1.10.1
Requires-Dist: torch >=2.0.1
Provides-Extra: dev
Requires-Dist: black ; extra == 'dev'
Requires-Dist: bumpver ; extra == 'dev'
Requires-Dist: isort ; extra == 'dev'
Requires-Dist: pip-tools ; extra == 'dev'
Requires-Dist: pytest ; extra == 'dev'
